{
	"info": {
		"_postman_id": "791c7424-c1d6-489e-98b5-c3a0cbeb16f3",
		"name": "flomobility-assignment_2-collection-aniket",
		"schema": "https://schema.getpostman.com/json/collection/v2.1.0/collection.json",
		"_exporter_id": "39955681"
	},
	"item": [
		{
			"name": "Auth",
			"item": [
				{
					"name": "Register Employer",
					"request": {
						"auth": {
							"type": "noauth"
						},
						"method": "POST",
						"header": [],
						"body": {
							"mode": "raw",
							"raw": "{\n    \"name\": \"Test Employer 1\",\n    \"email\": \"emp-1@test.com\",\n    \"password\": \"123\",\n    \"role\": \"employer\"\n}",
							"options": {
								"raw": {
									"language": "json"
								}
							}
						},
						"url": {
							"raw": "{{url}}/auth/register",
							"host": [
								"{{url}}"
							],
							"path": [
								"auth",
								"register"
							]
						}
					},
					"response": []
				},
				{
					"name": "Register Candidate",
					"request": {
						"auth": {
							"type": "noauth"
						},
						"method": "POST",
						"header": [],
						"body": {
							"mode": "raw",
							"raw": "{\n    \"name\": \"John Candidate\",\n    \"email\": \"john@test.com\",\n    \"password\": \"987\",\n    \"role\": \"candidate\"\n}",
							"options": {
								"raw": {
									"language": "json"
								}
							}
						},
						"url": {
							"raw": "{{url}}/auth/register",
							"host": [
								"{{url}}"
							],
							"path": [
								"auth",
								"register"
							]
						}
					},
					"response": []
				},
				{
					"name": "Login",
					"request": {
						"auth": {
							"type": "noauth"
						},
						"method": "POST",
						"header": [],
						"body": {
							"mode": "raw",
							"raw": "{\n    \"email\": \"john@test.com\",\n    \"password\": \"987\"\n}",
							"options": {
								"raw": {
									"language": "json"
								}
							}
						},
						"url": {
							"raw": "{{url}}/auth/login",
							"host": [
								"{{url}}"
							],
							"path": [
								"auth",
								"login"
							]
						}
					},
					"response": []
				},
				{
					"name": "Get Current User",
					"request": {
						"auth": {
							"type": "bearer",
							"bearer": [
								{
									"key": "token",
									"value": "<put-token-from-the-login-above>",
									"type": "string"
								}
							]
						},
						"method": "GET",
						"header": [],
						"url": {
							"raw": "{{url}}/auth/me",
							"host": [
								"{{url}}"
							],
							"path": [
								"auth",
								"me"
							]
						}
					},
					"response": []
				}
			],
			"auth": {
				"type": "noauth"
			}
		},
		{
			"name": "Jobs",
			"item": [
				{
					"name": "Create Job",
					"request": {
						"auth": {
							"type": "bearer",
							"bearer": [
								{
									"key": "token",
									"value": "<registered-employer-token>",
									"type": "string"
								}
							]
						},
						"method": "POST",
						"header": [],
						"body": {
							"mode": "raw",
							"raw": "{\n  \"title\": \"React Developer\",\n  \"company\": \"Big xyz company\",\n  \"location\": \"Remote\",\n  \"type\": \"Full-time\",\n  \"description\": \"We need a React dev.\",\n  \"salaryRange\": \"$100k\"\n}",
							"options": {
								"raw": {
									"language": "json"
								}
							}
						},
						"url": {
							"raw": "{{url}}/jobs",
							"host": [
								"{{url}}"
							],
							"path": [
								"jobs"
							]
						}
					},
					"response": []
				},
				{
					"name": "Get All Jobs",
					"request": {
						"auth": {
							"type": "noauth"
						},
						"method": "GET",
						"header": [],
						"url": {
							"raw": "{{url}}/jobs?search=React&location=Remote",
							"host": [
								"{{url}}"
							],
							"path": [
								"jobs"
							],
							"query": [
								{
									"key": "search",
									"value": "React"
								},
								{
									"key": "location",
									"value": "Remote"
								}
							]
						}
					},
					"response": []
				},
				{
					"name": "Get Single Job",
					"request": {
						"auth": {
							"type": "noauth"
						},
						"method": "GET",
						"header": [],
						"url": {
							"raw": "{{url}}/jobs/<paste_job_id_here>",
							"host": [
								"{{url}}"
							],
							"path": [
								"jobs",
								"<paste_job_id_here>"
							]
						}
					},
					"response": []
				},
				{
					"name": "Get Employer Jobs",
					"request": {
						"auth": {
							"type": "bearer",
							"bearer": [
								{
									"key": "token",
									"value": "{{token}}",
									"type": "string"
								}
							]
						},
						"method": "GET",
						"header": [],
						"url": {
							"raw": "{{url}}/jobs/employer/jobs",
							"host": [
								"{{url}}"
							],
							"path": [
								"jobs",
								"employer",
								"jobs"
							]
						}
					},
					"response": []
				},
				{
					"name": "Update Job",
					"request": {
						"auth": {
							"type": "bearer",
							"bearer": [
								{
									"key": "token",
									"value": "{{token}}",
									"type": "string"
								}
							]
						},
						"method": "PUT",
						"header": [],
						"body": {
							"mode": "raw",
							"raw": "{\"title\": \"Senior React Developer\"}",
							"options": {
								"raw": {
									"language": "json"
								}
							}
						},
						"url": {
							"raw": "{{url}}/jobs/<paste_job_id_here>",
							"host": [
								"{{url}}"
							],
							"path": [
								"jobs",
								"<paste_job_id_here>"
							]
						}
					},
					"response": []
				},
				{
					"name": "Delete Job",
					"request": {
						"auth": {
							"type": "bearer",
							"bearer": [
								{
									"key": "token",
									"value": "{{token}}",
									"type": "string"
								}
							]
						},
						"method": "DELETE",
						"header": [],
						"url": {
							"raw": "{{url}}/jobs/<paste_job_id_here>",
							"host": [
								"{{url}}"
							],
							"path": [
								"jobs",
								"<paste_job_id_here>"
							]
						}
					},
					"response": []
				}
			],
			"auth": {
				"type": "bearer",
				"bearer": [
					{
						"key": "token",
						"value": "<put your employer token here>",
						"type": "string"
					}
				]
			}
		},
		{
			"name": "Application",
			"item": [
				{
					"name": "Apply to Job (pdf file upload)",
					"request": {
						"auth": {
							"type": "bearer",
							"bearer": [
								{
									"key": "token",
									"value": "{{token}}",
									"type": "string"
								}
							]
						},
						"method": "POST",
						"header": [],
						"body": {
							"mode": "formdata",
							"formdata": [
								{
									"key": "jobId",
									"value": "69230e327d8a0b1527049a7e",
									"type": "text"
								},
								{
									"key": "resume",
									"type": "file",
									"src": "/home/aniketxd/Downloads/MyResume (2).pdf"
								}
							]
						},
						"url": {
							"raw": "{{url}}/applications",
							"host": [
								"{{url}}"
							],
							"path": [
								"applications"
							]
						}
					},
					"response": []
				},
				{
					"name": "Get My applications (candidate)",
					"request": {
						"auth": {
							"type": "bearer",
							"bearer": [
								{
									"key": "token",
									"value": "{{token}}",
									"type": "string"
								}
							]
						},
						"method": "GET",
						"header": [],
						"url": {
							"raw": "{{url}}/applications/my",
							"host": [
								"{{url}}"
							],
							"path": [
								"applications",
								"my"
							]
						}
					},
					"response": []
				},
				{
					"name": "View job applications (posted by employer)",
					"request": {
						"auth": {
							"type": "bearer",
							"bearer": [
								{
									"key": "token",
									"value": "<put employer token here>",
									"type": "string"
								}
							]
						},
						"method": "GET",
						"header": [],
						"url": {
							"raw": "{{url}}/jobs/:id/applications",
							"host": [
								"{{url}}"
							],
							"path": [
								"jobs",
								":id",
								"applications"
							],
							"variable": [
								{
									"key": "id",
									"value": "",
									"type": "string"
								}
							]
						}
					},
					"response": []
				},
				{
					"name": "update status (employer)",
					"request": {
						"auth": {
							"type": "bearer",
							"bearer": [
								{
									"key": "token",
									"value": "<put employer token here>",
									"type": "string"
								}
							]
						},
						"method": "PUT",
						"header": [],
						"body": {
							"mode": "raw",
							"raw": "{\"status\": \"interview\"}",
							"options": {
								"raw": {
									"language": "json"
								}
							}
						},
						"url": {
							"raw": "{{url}}/applications/:id/status",
							"host": [
								"{{url}}"
							],
							"path": [
								"applications",
								":id",
								"status"
							],
							"variable": [
								{
									"key": "id",
									"value": "",
									"type": "string"
								}
							]
						}
					},
					"response": []
				},
				{
					"name": "withdraw application (candidate)",
					"request": {
						"auth": {
							"type": "bearer",
							"bearer": [
								{
									"key": "token",
									"value": "{{token}}",
									"type": "string"
								}
							]
						},
						"method": "PUT",
						"header": [],
						"url": {
							"raw": "{{url}}/applications/<applicationid: _id>/withdraw",
							"host": [
								"{{url}}"
							],
							"path": [
								"applications",
								"<applicationid: _id>",
								"withdraw"
							]
						}
					},
					"response": []
				}
			],
			"auth": {
				"type": "bearer",
				"bearer": [
					{
						"key": "token",
						"value": "<put your candidate token here>",
						"type": "string"
					}
				]
			}
		}
	],
	"variable": [
		{
			"key": "url",
			"value": "http://localhost:5000/api",
			"type": "string"
		},
		{
			"key": "token",
			"value": "",
			"type": "string"
		}
	]
}